django_command_form/__init__.py
django_command_form/admin.py
django_command_form/command.py
django_command_form/forms.py
django_command_form/models.py
django_command_form/parser_types.py
django_command_form/templates/command/exec_done.html
django_command_form/templates/command/exec_form.html
django_command_form-0.0.5.dist-info/LICENSE
django_command_form-0.0.5.dist-info/METADATA
django_command_form-0.0.5.dist-info/WHEEL
django_command_form-0.0.5.dist-info/top_level.txt
django_command_form-0.0.5.dist-info/RECORD
