Metadata-Version: 2.2
Name: django-command-form
Version: 0.0.5
Summary: A package that allows you to execute commands from DjangoAdmin.
Home-page: http://github.com/naohide/django-command-form/
Author: naohide
Author-email: n.anahara@fragment.co.jp
License: MIT
License-File: LICENSE
Requires-Dist: Django>=4.0
Dynamic: author
Dynamic: author-email
Dynamic: description
Dynamic: description-content-type
Dynamic: home-page
Dynamic: license
Dynamic: requires-dist
Dynamic: summary
